setup.py
wordnik/__init__.py
wordnik.egg-info/PKG-INFO
wordnik.egg-info/SOURCES.txt
wordnik.egg-info/dependency_links.txt
wordnik.egg-info/top_level.txt
wordnik/api/APIClient.py
wordnik/api/AccountAPI.py
wordnik/api/VersionChecker.py
wordnik/api/WordAPI.py
wordnik/api/WordListAPI.py
wordnik/api/WordsAPI.py
wordnik/api/__init__.py
wordnik/model/ApiTokenStatus.py
wordnik/model/AudioFile.py
wordnik/model/AudioType.py
wordnik/model/AuthenticationToken.py
wordnik/model/Bigram.py
wordnik/model/CaseSensitiveValues.py
wordnik/model/Category.py
wordnik/model/Citation.py
wordnik/model/ContentProvider.py
wordnik/model/Definition.py
wordnik/model/Example.py
wordnik/model/ExampleSearchResults.py
wordnik/model/ExampleUsage.py
wordnik/model/ExcludePartOfSpeechValues.py
wordnik/model/Facet.py
wordnik/model/FacetValue.py
wordnik/model/Frequency.py
wordnik/model/FrequencySummary.py
wordnik/model/HasDictionaryDefValues.py
wordnik/model/IncludeDuplicatesValues.py
wordnik/model/IncludePartOfSpeechValues.py
wordnik/model/IncludeRelatedValues.py
wordnik/model/IncludeSuggestionsValues.py
wordnik/model/IncludeTagsValues.py
wordnik/model/Label.py
wordnik/model/Note.py
wordnik/model/PartOfSpeech.py
wordnik/model/PartOfSpeechValues.py
wordnik/model/Related.py
wordnik/model/Root.py
wordnik/model/ScoredWord.py
wordnik/model/Sentence.py
wordnik/model/SortByValues.py
wordnik/model/SortOrderValues.py
wordnik/model/SourceDictionariesValues.py
wordnik/model/SourceDictionaryValues.py
wordnik/model/String.py
wordnik/model/StringValue.py
wordnik/model/Syllable.py
wordnik/model/TestData.py
wordnik/model/TextPron.py
wordnik/model/TypeFormatValues.py
wordnik/model/TypeValues.py
wordnik/model/UseCanonicalValues.py
wordnik/model/User.py
wordnik/model/WordDefinitionsInput.py
wordnik/model/WordExamplesInput.py
wordnik/model/WordFrequency.py
wordnik/model/WordList.py
wordnik/model/WordListWord.py
wordnik/model/WordListWordsInput.py
wordnik/model/WordObject.py
wordnik/model/WordOfTheDay.py
wordnik/model/WordPronunciationsInput.py
wordnik/model/WordRelatedInput.py
wordnik/model/WordSearchResult.py
wordnik/model/WordSearchResults.py
