Metadata-Version: 1.0
Name: wordnik
Version: 2.0
Summary: Wordnik API for Python
Home-page: http://developer.wordnik.com
Author: Robin Walsh
Author-email: robin@wordnik.com
License: UNKNOWN
Platform: UNKNOWN
